AUTHORS
LICENSE
MANIFEST.in
README.rst
run_tests.py
setup.cfg
setup.py
django10_enumfield.egg-info/PKG-INFO
django10_enumfield.egg-info/SOURCES.txt
django10_enumfield.egg-info/dependency_links.txt
django10_enumfield.egg-info/top_level.txt
django_enumfield/__init__.py
django_enumfield/enum.py
django_enumfield/exceptions.py
django_enumfield/models.py
django_enumfield/validators.py
django_enumfield/__pycache__/__init__.cpython-35.pyc
django_enumfield/__pycache__/enum.cpython-35.pyc
django_enumfield/__pycache__/exceptions.cpython-35.pyc
django_enumfield/__pycache__/models.cpython-35.pyc
django_enumfield/__pycache__/validators.cpython-35.pyc
django_enumfield/db/__init__.py
django_enumfield/db/fields.py
django_enumfield/db/__pycache__/__init__.cpython-35.pyc
django_enumfield/db/__pycache__/fields.cpython-35.pyc
django_enumfield/tests/__init__.py
django_enumfield/tests/models.py
django_enumfield/tests/test_enum.py
django_enumfield/tests/test_settings.py
django_enumfield/tests/test_validators.py
django_enumfield/tests/urls.py
django_enumfield/tests/__pycache__/__init__.cpython-35.pyc
django_enumfield/tests/__pycache__/models.cpython-35.pyc
django_enumfield/tests/__pycache__/test_enum.cpython-35.pyc
django_enumfield/tests/__pycache__/test_settings.cpython-35.pyc
django_enumfield/tests/__pycache__/test_validators.cpython-35.pyc
django_enumfield/tests/__pycache__/urls.cpython-35.pyc