Metadata-Version: 1.1
Name: django10-enumfield
Version: 1.4
Summary: Custom Django field for using enumerations of named constants
Home-page: https://github.com/i2biz/django-enumfield
Author: Jacek Bzdak
Author-email: jacek@askesis.pl
License: MIT
Keywords: django,enum,field,status,state,choices,form,model
Platform: any
Classifier: Programming Language :: Python
Classifier: Programming Language :: Python :: 2
Classifier: Programming Language :: Python :: 2.7
Classifier: Programming Language :: Python :: 3
Classifier: Programming Language :: Python :: 3.4
Classifier: Programming Language :: Python :: 3.5
Classifier: Framework :: Django
Classifier: Natural Language :: English
Classifier: Environment :: Web Environment
Classifier: Intended Audience :: Developers
Classifier: License :: OSI Approved :: MIT License
Classifier: Operating System :: OS Independent
Classifier: Topic :: Utilities
Classifier: Topic :: Software Development :: Libraries :: Python Modules
